swid_generator/__init__.py
swid_generator/argparser.py
swid_generator/argparser_helper.py
swid_generator/command_manager.py
swid_generator/exceptions.py
swid_generator/main.py
swid_generator/meta.py
swid_generator/package_info.py
swid_generator/patches.py
swid_generator/print_functions.py
swid_generator/settings.py
swid_generator/signature_template.py
swid_generator/environments/__init__.py
swid_generator/environments/common.py
swid_generator/environments/dpkg_environment.py
swid_generator/environments/environment_registry.py
swid_generator/environments/pacman_environment.py
swid_generator/environments/rpm_environment.py
swid_generator/generators/__init__.py
swid_generator/generators/content_creator.py
swid_generator/generators/softwareid_generator.py
swid_generator/generators/swid_generator.py
swid_generator/generators/utils.py
swid_generator-1.1.0.dist-info/DESCRIPTION.rst
swid_generator-1.1.0.dist-info/METADATA
swid_generator-1.1.0.dist-info/RECORD
swid_generator-1.1.0.dist-info/WHEEL
swid_generator-1.1.0.dist-info/entry_points.txt
swid_generator-1.1.0.dist-info/metadata.json
swid_generator-1.1.0.dist-info/top_level.txt
swid_generator-1.1.0.dist-info/zip-safe
