Metadata-Version: 2.0
Name: swid-generator
Version: 1.1.0
Summary: Application which generates SWID-Tags from Linux installed packages, package-files and directories using tools like DPGK or RPM.
Home-page: https://github.com/strongswan/swidGenerator
Author: Christian Fässler, Danilo Bargen, Jonas Furrer, Davide De Giorgio, Christof Greiner, Andreas Steffen, Tobias Brunner
Author-email: UNKNOWN
License: MIT
Keywords: swid dpkg rpm pacman tnc
Platform: UNKNOWN
Classifier: Development Status :: 5 - Production/Stable
Classifier: Environment :: Console
Classifier: Intended Audience :: Information Technology
Classifier: Intended Audience :: System Administrators
Classifier: License :: OSI Approved :: MIT License
Classifier: Operating System :: POSIX :: Linux
Classifier: Programming Language :: Python :: 2
Classifier: Programming Language :: Python :: 2.7
Classifier: Programming Language :: Python :: 3
Classifier: Programming Language :: Python :: 3.5
Classifier: Programming Language :: Python :: 3.6
Classifier: Programming Language :: Python :: 3.7
Classifier: Programming Language :: Python :: 3.8
Requires-Dist: distro
